face_parsing/model.py
face_parsing/resnet.py
face_parsing/segment.py
face_parsing-0.2.dist-info/LICENSE
face_parsing-0.2.dist-info/METADATA
face_parsing-0.2.dist-info/WHEEL
face_parsing-0.2.dist-info/entry_points.txt
face_parsing-0.2.dist-info/top_level.txt
face_parsing-0.2.dist-info/RECORD
