Metadata-Version: 2.1
Name: face_parsing
Version: 0.2
Summary: This repo is used to generate semantic segmentation for face image
Home-page: https://github.com/sword4869/face_parsing
Author: sword4869
License-File: LICENSE
Requires-Dist: configargparse
Requires-Dist: opencv-contrib-python
Requires-Dist: numpy
Requires-Dist: pillow
Requires-Dist: tqdm
Requires-Dist: torch
Requires-Dist: torchvision
